LICENSE
MANIFEST.in
README.md
config_default.txt
requirements.txt
setup.py
bin/dropbox_uploader.sh
bin/llp
data/CorrectionRules.txt.gz
data/contentwords.byu.txt.gz
data/spelling_variants_from_morphadorner.txt.gz
data/stopwords.byu.txt.gz
data/stopwords.onix.txt.gz
data/wordlist.aspell.net.with_caps.txt.gz
llp/__init__.py
llp/llp.py
llp.egg-info/PKG-INFO
llp.egg-info/SOURCES.txt
llp.egg-info/dependency_links.txt
llp.egg-info/requires.txt
llp.egg-info/top_level.txt
llp/corpus/__init__.py
llp/corpus/corpus.py
llp/corpus/manifest.txt
llp/corpus/bpo/__init__.py
llp/corpus/bpo/bpo.py
llp/corpus/chadwyck/__init__.py
llp/corpus/chadwyck/chadwyck.py
llp/corpus/chadwyck_drama/__init__.py
llp/corpus/chadwyck_drama/chadwyck_drama.py
llp/corpus/chadwyck_poetry/__init__.py
llp/corpus/chadwyck_poetry/chadwyck_poetry.py
llp/corpus/chicago/__init__.py
llp/corpus/chicago/chicago.py
llp/corpus/clmet/__init__.py
llp/corpus/clmet/clmet.py
llp/corpus/coha/__init__.py
llp/corpus/coha/coha.py
llp/corpus/default/__init__.py
llp/corpus/default/default.py
llp/corpus/default/new_corpus.py
llp/corpus/dialnarr/__init__.py
llp/corpus/dialnarr/dialnarr.py
llp/corpus/dialogues/__init__.py
llp/corpus/dialogues/dialogues.py
llp/corpus/dottxt/__init__.py
llp/corpus/dottxt/dottxt.py
llp/corpus/ecco/README.md
llp/corpus/ecco/__init__.py
llp/corpus/ecco/ecco.py
llp/corpus/eebo/__init__.py
llp/corpus/eebo/eebo.py
llp/corpus/estc/__init__.py
llp/corpus/estc/estc.py
llp/corpus/fictio/__init__.py
llp/corpus/fictio/fictio.py
llp/corpus/gale_amfic/__init__.py
llp/corpus/gale_amfic/gale_amfic.py
llp/corpus/gildedage/__init__.py
llp/corpus/gildedage/gildedage.py
llp/corpus/lithist/__init__.py
llp/corpus/lithist/lithist.py
llp/corpus/litlab/__init__.py
llp/corpus/litlab/litlab.py
llp/corpus/long18c/__init__.py
llp/corpus/long18c/long18c.py
llp/corpus/markmark/__init__.py
llp/corpus/markmark/markmark.py
llp/corpus/oldbailey/__init__.py
llp/corpus/oldbailey/oldbailey.py
llp/corpus/ravengarside/__init__.py
llp/corpus/ravengarside/ravengarside.py
llp/corpus/sellars/__init__.py
llp/corpus/sellars/sellars.py
llp/corpus/spectator/__init__.py
