Metadata-Version: 2.1
Name: llp
Version: 0.2.2
Summary: Literary Language Processing (LLP): corpora, models, and tools for the digital humanities
Home-page: https://github.com/quadrismegistus/llp
Author: Ryan Heuser
Author-email: heuser@stanford.edu
License: MIT
Platform: UNKNOWN
